{
	"archive" : {},
	"artifacts" : 
	[
		{
			"path" : "MConfig/libMConfig.a"
		}
	],
	"backtrace" : 1,
	"backtraceGraph" : 
	{
		"commands" : 
		[
			"add_library",
			"target_link_libraries",
			"add_compile_definitions",
			"include_directories",
			"target_include_directories"
		],
		"files" : 
		[
			"MConfig/CMakeLists.txt",
			"CMakeLists.txt"
		],
		"nodes" : 
		[
			{
				"file" : 0
			},
			{
				"command" : 0,
				"file" : 0,
				"line" : 3,
				"parent" : 0
			},
			{
				"command" : 1,
				"file" : 0,
				"line" : 13,
				"parent" : 0
			},
			{
				"file" : 1
			},
			{
				"command" : 2,
				"file" : 1,
				"line" : 6,
				"parent" : 3
			},
			{
				"command" : 3,
				"file" : 0,
				"line" : 5,
				"parent" : 0
			},
			{
				"command" : 4,
				"file" : 0,
				"line" : 8,
				"parent" : 0
			}
		]
	},
	"compileGroups" : 
	[
		{
			"compileCommandFragments" : 
			[
				{
					"fragment" : "-g"
				},
				{
					"fragment" : "-std=gnu++14"
				}
			],
			"defines" : 
			[
				{
					"backtrace" : 4,
					"define" : "TEST"
				}
			],
			"includes" : 
			[
				{
					"backtrace" : 5,
					"path" : "D:/Project/TestMe/cmake-build-debug-mingw/MConfig"
				},
				{
					"backtrace" : 6,
					"path" : "D:/Project/TestMe/Mutils"
				},
				{
					"backtrace" : 6,
					"path" : "D:/Project/TestMe/ThirdParty"
				}
			],
			"language" : "CXX",
			"languageStandard" : 
			{
				"backtraces" : 
				[
					1
				],
				"standard" : "14"
			},
			"sourceIndexes" : 
			[
				0,
				1,
				2,
				3
			]
		}
	],
	"dependencies" : 
	[
		{
			"backtrace" : 2,
			"id" : "Mutils::@aa137bdceb208c777fd2"
		}
	],
	"id" : "MConfig::@8c13a2ee92a5612cc6bd",
	"name" : "MConfig",
	"nameOnDisk" : "libMConfig.a",
	"paths" : 
	{
		"build" : "MConfig",
		"source" : "MConfig"
	},
	"sourceGroups" : 
	[
		{
			"name" : "Source Files",
			"sourceIndexes" : 
			[
				0,
				1,
				2,
				3
			]
		}
	],
	"sources" : 
	[
		{
			"backtrace" : 1,
			"compileGroupIndex" : 0,
			"path" : "MConfig/GlobalConfig.cpp",
			"sourceGroupIndex" : 0
		},
		{
			"backtrace" : 1,
			"compileGroupIndex" : 0,
			"path" : "MConfig/IniConfig.cpp",
			"sourceGroupIndex" : 0
		},
		{
			"backtrace" : 1,
			"compileGroupIndex" : 0,
			"path" : "MConfig/YamlConfig.cpp",
			"sourceGroupIndex" : 0
		},
		{
			"backtrace" : 1,
			"compileGroupIndex" : 0,
			"path" : "MConfig/iConfig.cpp",
			"sourceGroupIndex" : 0
		}
	],
	"type" : "STATIC_LIBRARY"
}
